optiontools
